odoo10_addon_storage_image-10.0.1.1.1-py3.8-nspkg.pth
odoo/addons/storage_image/README.rst
odoo/addons/storage_image/__init__.py
odoo/addons/storage_image/__manifest__.py
odoo/addons/storage_image/data/ir_parameter.xml
odoo/addons/storage_image/i18n/storage_image.pot
odoo/addons/storage_image/models/__init__.py
odoo/addons/storage_image/models/image_relation_abstract.py
odoo/addons/storage_image/models/storage_file.py
odoo/addons/storage_image/models/storage_image.py
odoo/addons/storage_image/security/ir.model.access.csv
odoo/addons/storage_image/security/ir_rule.xml
odoo/addons/storage_image/security/res_group.xml
odoo/addons/storage_image/static/description/icon.png
odoo/addons/storage_image/static/src/css/image_handle.css
odoo/addons/storage_image/static/src/js/image_handle.js
odoo/addons/storage_image/static/src/js/storage_image.js
odoo/addons/storage_image/tests/__init__.py
odoo/addons/storage_image/tests/test_storage_image.py
odoo/addons/storage_image/tests/static/akretion-logo.png
odoo/addons/storage_image/views/js.xml
odoo/addons/storage_image/views/storage_image_view.xml
odoo10_addon_storage_image-10.0.1.1.1.dist-info/METADATA
odoo10_addon_storage_image-10.0.1.1.1.dist-info/WHEEL
odoo10_addon_storage_image-10.0.1.1.1.dist-info/namespace_packages.txt
odoo10_addon_storage_image-10.0.1.1.1.dist-info/top_level.txt
odoo10_addon_storage_image-10.0.1.1.1.dist-info/RECORD
